openscenesense/__init__.py
openscenesense/analyzer.py
openscenesense/frame_selectors.py
openscenesense/models.py
openscenesense/openrouter_analyzer.py
openscenesense-1.1.0.dist-info/METADATA
openscenesense-1.1.0.dist-info/WHEEL
openscenesense-1.1.0.dist-info/licenses/LICENSE
openscenesense-1.1.0.dist-info/RECORD
