Metadata-Version: 2.4
Name: openscenesense
Version: 1.1.0
Summary: A video analysis toolkit using OpenAI and Openrouter vision models
Project-URL: Homepage, https://github.com/ymrohit/openscenesense
Project-URL: Bug Tracker, https://github.com/ymrohit/openscenesense/issues
Author-email: Rohit Yelukati Mahendra <mahendrarohittigon@gmail.com>
License-File: LICENSE
Classifier: License :: OSI Approved :: MIT License
Classifier: Operating System :: OS Independent
Classifier: Programming Language :: Python :: 3
Requires-Python: >=3.10
Requires-Dist: ffmpeg-python>=0.2.0
Requires-Dist: librosa>=0.10.2.post1
Requires-Dist: numpy>=2.0.2
Requires-Dist: openai>=1.53.0
Requires-Dist: opencv-python>=4.10.0
Requires-Dist: pillow>=11.0.0
Requires-Dist: soundfile>=0.12.0
